{
  "series": "Log Horizon",
  "thumbnail": "https://image.tmdb.org/t/p/w185/vrCAD2KvtGJPwABIPd4z0gChi4g.jpg",
  "season": 1,
  "episode": 25,
  "episode_title": "Episode 25",
  "episode_main_poster": "https://image.tmdb.org/t/p/w185/vrCAD2KvtGJPwABIPd4z0gChi4g.jpg",
  "episode_card_thumbnail": "https://image.tmdb.org/t/p/w185/zYqouuva2rBVAp58aF6X4ju0mNZ.jpg",
  "episode_list_thumbnail": "https://image.tmdb.org/t/p/w185/zYqouuva2rBVAp58aF6X4ju0mNZ.jpg",
  "video_player_thumbnail": null,
  "servers": [
    {
      "option": 1,
      "real_video": "https://vidstreaming.xyz/v/aCpJVabOp2RA/"
    },
    {
      "option": 2,
      "real_video": "https://rubystm.com/e/qfuddd94utd7.html"
    },
    {
      "option": 3,
      "real_video": "https://short.icu/bXBkCtLXn"
    },
    {
      "option": 4,
      "real_video": "https://gdmirrorbot.nl/embed/fd9k9uz"
    },
    {
      "option": 5,
      "real_video": "https://gdmirrorbot.nl/embed/apzuq8m"
    },
    {
      "option": 6,
      "real_video": "https://gdmirrorbot.nl/embed/qv97x9t"
    },
    {
      "option": null,
      "real_video": "https://play.zephyrflick.top/video/d198bd736a97e7cecfdf8f4f2027ef80"
    }
  ]
}