{
  "series": "Dan Da Dan",
  "thumbnail": "https://image.tmdb.org/t/p/w185/qU12CrNOYdxwlx7wvrhpgo2q1XQ.jpg",
  "season": 2,
  "episode": 9,
  "episode_title": "Episode 9",
  "episode_main_poster": "https://image.tmdb.org/t/p/w185/qU12CrNOYdxwlx7wvrhpgo2q1XQ.jpg",
  "episode_card_thumbnail": "https://image.tmdb.org/t/p/w185/hC4YDLfbW7B5KpRJczOdPP3Mflp.jpg",
  "episode_list_thumbnail": "https://image.tmdb.org/t/p/w185/hC4YDLfbW7B5KpRJczOdPP3Mflp.jpg",
  "video_player_thumbnail": null,
  "servers": [
    {
      "option": 1,
      "real_video": "https://short.icu/TaLkANfvQ"
    },
    {
      "option": 2,
      "real_video": "https://rubystm.com/e/50zli90r5pir.html"
    },
    {
      "option": 3,
      "real_video": "https://cloudy.upns.one/#5zuwtm"
    },
    {
      "option": 4,
      "real_video": "https://strmup.to/UNmIqb1DKgAas"
    },
    {
      "option": 5,
      "real_video": "https://gdmirrorbot.nl/embed/wb9j8fb"
    },
    {
      "option": 6,
      "real_video": "https://gdmirrorbot.nl/embed/semuhpo"
    },
    {
      "option": 7,
      "real_video": "https://gdmirrorbot.nl/embed/oc28tu0"
    },
    {
      "option": 8,
      "real_video": "https://emturbovid.com/t/68b0996b39ba6"
    },
    {
      "option": 9,
      "real_video": "https://vidmoly.net/embed-ja8rom3fbzjm.html"
    },
    {
      "option": null,
      "real_video": "https://play.zephyrflick.top/video/fc73483cfec371c61e8f755f0ed49da4"
    }
  ]
}