{
  "series": "Overlord",
  "thumbnail": "https://image.tmdb.org/t/p/w185/zjSAukWORQxJAJjpR1KBk5X77PP.jpg",
  "season": 4,
  "episode": 12,
  "episode_title": "Episode 12",
  "episode_main_poster": "https://image.tmdb.org/t/p/w185/zjSAukWORQxJAJjpR1KBk5X77PP.jpg",
  "episode_card_thumbnail": "https://image.tmdb.org/t/p/w185/u449dFidrESWD0cIw9nvEO8eLRo.jpg",
  "episode_list_thumbnail": "https://image.tmdb.org/t/p/w185/u449dFidrESWD0cIw9nvEO8eLRo.jpg",
  "video_player_thumbnail": null,
  "servers": [
    {
      "option": 1,
      "real_video": "https://rubystm.com/e/a70oqlqqh6ap.html"
    },
    {
      "option": 2,
      "real_video": "https://cloudy.upns.one/#jco1r8"
    },
    {
      "option": 3,
      "real_video": "https://strmup.to/TcUWbENCI0mSv"
    },
    {
      "option": 4,
      "real_video": "https://animeworld.site/embed/64196/4-12"
    },
    {
      "option": null,
      "real_video": "https://short.icu/TG0Um4JuW"
    }
  ]
}