{
  "series": "Solo Leveling",
  "thumbnail": "https://image.tmdb.org/t/p/w185/rsOApVLbIQEcNkqSlOxNPyg3FyI.jpg",
  "season": 1,
  "episode": 4,
  "episode_title": "Episode 4",
  "episode_main_poster": "https://image.tmdb.org/t/p/w185/rsOApVLbIQEcNkqSlOxNPyg3FyI.jpg",
  "episode_card_thumbnail": "https://image.tmdb.org/t/p/w185/2zbHJNbyuGEdyGVOyJpv24qgf2w.jpg",
  "episode_list_thumbnail": "https://image.tmdb.org/t/p/w185/2zbHJNbyuGEdyGVOyJpv24qgf2w.jpg",
  "video_player_thumbnail": null,
  "servers": [
    {
      "option": 1,
      "real_video": "https://short.icu/B8Lo_TDgs"
    },
    {
      "option": 2,
      "real_video": "https://rubystm.com/e/3i46oimd4u02.html"
    },
    {
      "option": 3,
      "real_video": "https://cloudy.upns.one/#ipzq39"
    },
    {
      "option": 4,
      "real_video": "https://strmup.to/mTfjyLd1NFaAu"
    },
    {
      "option": 5,
      "real_video": "https://turbovidhls.com/t/68bfab1fa9540"
    },
    {
      "option": 6,
      "real_video": "https://vidmoly.net/embed-m2s1bgm8d8me.html"
    },
    {
      "option": 7,
      "real_video": "https://blakiteapi.xyz/embed/127532/1-4"
    },
    {
      "option": 8,
      "real_video": "https://gdmirrorbot.nl/embed/snddppv"
    },
    {
      "option": 9,
      "real_video": "https://gdmirrorbot.nl/embed/fx32xk4"
    },
    {
      "option": 10,
      "real_video": "https://gdmirrorbot.nl/embed/il4wec6"
    },
    {
      "option": null,
      "real_video": "https://play.zephyrflick.top/video/885fd739d31951206a8c4f0d6472fcf0"
    }
  ]
}