{
  "series": "One Piece",
  "thumbnail": "https://image.tmdb.org/t/p/w185/dum1wnm6kJOUos0XJqjB8s2UWi9.jpg",
  "season": 21,
  "episode": 123,
  "episode_title": "Episode 123",
  "episode_main_poster": "https://image.tmdb.org/t/p/w185/dum1wnm6kJOUos0XJqjB8s2UWi9.jpg",
  "episode_card_thumbnail": "https://image.tmdb.org/t/p/w185/myceegU1flX3KkzFb8nQZzbpVlx.jpg",
  "episode_list_thumbnail": "https://image.tmdb.org/t/p/w185/myceegU1flX3KkzFb8nQZzbpVlx.jpg",
  "video_player_thumbnail": null,
  "servers": [
    {
      "option": 1,
      "real_video": "https://vidstreaming.xyz/v/EbbpNVMbSDiS/"
    },
    {
      "option": 2,
      "real_video": "https://short.icu/Syt9kNtiC"
    },
    {
      "option": 3,
      "real_video": "https://rubystm.com/e/y4n7uz7q05hf.html"
    },
    {
      "option": null,
      "real_video": "https://vidstreaming.xyz/v/LyGTCFwQV4mB/"
    }
  ]
}