{
  "series": "One Piece",
  "thumbnail": "https://image.tmdb.org/t/p/w185/dum1wnm6kJOUos0XJqjB8s2UWi9.jpg",
  "season": 21,
  "episode": 156,
  "episode_title": "Episode 156",
  "episode_main_poster": "https://image.tmdb.org/t/p/w185/dum1wnm6kJOUos0XJqjB8s2UWi9.jpg",
  "episode_card_thumbnail": "https://image.tmdb.org/t/p/w185/qUihSjNlaXmx6wXHJsbiaZlnUqA.jpg",
  "episode_list_thumbnail": "https://image.tmdb.org/t/p/w185/qUihSjNlaXmx6wXHJsbiaZlnUqA.jpg",
  "video_player_thumbnail": null,
  "servers": [
    {
      "option": 1,
      "real_video": "https://vidstreaming.xyz/v/U9u9GdWmmLUf/"
    },
    {
      "option": 2,
      "real_video": "https://short.icu/GUvVrVoo6"
    },
    {
      "option": 3,
      "real_video": "https://rubystm.com/e/rm8n9w0uuipl.html"
    },
    {
      "option": null,
      "real_video": "https://vidstreaming.xyz/v/mZrUzbRZX0Fm/"
    }
  ]
}