{
  "series": "Pokémon",
  "thumbnail": "https://image.tmdb.org/t/p/w185/rOuGm07PxBhEsK9TaGPRQVJQm1X.jpg",
  "season": 1,
  "episode": 27,
  "episode_title": "Episode 27",
  "episode_main_poster": "https://image.tmdb.org/t/p/w185/rOuGm07PxBhEsK9TaGPRQVJQm1X.jpg",
  "episode_card_thumbnail": "https://image.tmdb.org/t/p/w185/vNttWRnN1LEuzYUbVsfi5seFzEZ.jpg",
  "episode_list_thumbnail": "https://image.tmdb.org/t/p/w185/vNttWRnN1LEuzYUbVsfi5seFzEZ.jpg",
  "video_player_thumbnail": null,
  "servers": [
    {
      "option": null,
      "real_video": "https://vidstreaming.xyz/v/t8zmjhghQnjN/"
    }
  ]
}