{
  "series": "Jujutsu Kaisen",
  "thumbnail": "https://image.tmdb.org/t/p/w185/3yFHMtdhriig4sm1w8oMQfA2gFN.jpg",
  "season": 1,
  "episode": 1,
  "episode_title": "Episode 1",
  "episode_main_poster": "https://image.tmdb.org/t/p/w185/3yFHMtdhriig4sm1w8oMQfA2gFN.jpg",
  "episode_card_thumbnail": "https://image.tmdb.org/t/p/w185/veG3J8KaBudM8omuGi58fYOMDTz.jpg",
  "episode_list_thumbnail": "https://image.tmdb.org/t/p/w185/veG3J8KaBudM8omuGi58fYOMDTz.jpg",
  "video_player_thumbnail": null,
  "servers": [
    {
      "option": 1,
      "real_video": "https://filemoon.to/e/73w6r60es9o3/_Toonhub4u__Jujutsu_Kaisen_S01E01__BDRip_480p_x264___Multi_Audio__ESub"
    },
    {
      "option": 2,
      "real_video": "https://vidstreaming.xyz/v/zVkU8PXKEpzT/"
    },
    {
      "option": 3,
      "real_video": "https://rubystm.com/e/dzdfxnzp5vqu.html"
    },
    {
      "option": 4,
      "real_video": "https://embedwish.com/e/2qvxcywnppnu"
    },
    {
      "option": 5,
      "real_video": "https://filemoon.to/e/46nfgntf1lyr/_Toonhub4u__Jujutsu_Kaisen_S01E01__BDRip_480p_x264___Multi_Audio__ESub"
    },
    {
      "option": 6,
      "real_video": "https://filelions.online/v/o7xiva3gvdor"
    },
    {
      "option": 7,
      "real_video": "https://vidstreaming.xyz/v/G6fr1BclPvzU/"
    },
    {
      "option": 8,
      "real_video": "https://rubystm.com/e/ftn7lyuggq5a.html"
    },
    {
      "option": null,
      "real_video": "https://vidstreaming.xyz/v/GAtCPLGzMQqv/"
    }
  ]
}