{
  "series": "Sword Art Online",
  "thumbnail": "https://image.tmdb.org/t/p/w185/kuXL3UDa5TqCRat0az62hCJDeYE.jpg",
  "season": 2,
  "episode": 8,
  "episode_title": "Episode 8",
  "episode_main_poster": "https://image.tmdb.org/t/p/w185/kuXL3UDa5TqCRat0az62hCJDeYE.jpg",
  "episode_card_thumbnail": "https://image.tmdb.org/t/p/w185/3htNh1oP2IZjXTf2ej2H4ZynxKW.jpg",
  "episode_list_thumbnail": "https://image.tmdb.org/t/p/w185/3htNh1oP2IZjXTf2ej2H4ZynxKW.jpg",
  "video_player_thumbnail": null,
  "servers": [
    {
      "option": 1,
      "real_video": "https://vidstreaming.xyz/v/Tow14RdXtpj5/"
    },
    {
      "option": 2,
      "real_video": "https://short.icu/A5_2zQZxH"
    },
    {
      "option": 3,
      "real_video": "https://rubystm.com/e/e53nxj6wjty9.html"
    },
    {
      "option": 4,
      "real_video": "https://gdmirrorbot.nl/embed/p91v7lu"
    },
    {
      "option": 5,
      "real_video": "https://gdmirrorbot.nl/embed/mtl0nvl"
    },
    {
      "option": 6,
      "real_video": "https://gdmirrorbot.nl/embed/oeehecr"
    },
    {
      "option": 7,
      "real_video": "https://emturbovid.com/t/671e49553d1cd"
    },
    {
      "option": null,
      "real_video": "https://play.zephyrflick.top/video/5d5c18e4cd078a34b4db2ac85fbc1ed0"
    }
  ]
}