{
  "series": "Power Rangers Mighty Morphin (S1-3)",
  "thumbnail": "https://image.tmdb.org/t/p/w185/8lnX8RWeGBdEQPOvf2IKoRtKfZO.jpg",
  "season": 1,
  "episode": 6,
  "episode_title": "Episode 6",
  "episode_main_poster": "https://image.tmdb.org/t/p/w185/8lnX8RWeGBdEQPOvf2IKoRtKfZO.jpg",
  "episode_card_thumbnail": "https://image.tmdb.org/t/p/w185/mes6aVKlTOUyJF9wzMgG3th74bC.jpg",
  "episode_list_thumbnail": "https://image.tmdb.org/t/p/w185/mes6aVKlTOUyJF9wzMgG3th74bC.jpg",
  "video_player_thumbnail": null,
  "servers": [
    {
      "option": 1,
      "real_video": "https://short.icu/jSWmm6WD2"
    },
    {
      "option": 2,
      "real_video": "https://rubystm.com/e/p0m2p7r1amx7.html"
    },
    {
      "option": 3,
      "real_video": "https://cloudy.upns.one/#r8upov"
    },
    {
      "option": 4,
      "real_video": "https://strmup.to/SO2z3prHTvLU5"
    },
    {
      "option": 5,
      "real_video": "https://turbovidhls.com/t/68df7523127c1"
    },
    {
      "option": 6,
      "real_video": "https://vidmoly.net/embed-ahausegpe2cx.html"
    },
    {
      "option": null,
      "real_video": "https://vidstreaming.xyz/v/uGzbMyQ2JZiG/"
    }
  ]
}