{
  "series": "Dragon Ball Super",
  "thumbnail": "https://image.tmdb.org/t/p/w185/qEUrbXJ2qt4Rg84Btlx4STOhgte.jpg",
  "season": 1,
  "episode": 68,
  "episode_title": "Episode 68",
  "episode_main_poster": "https://image.tmdb.org/t/p/w185/qEUrbXJ2qt4Rg84Btlx4STOhgte.jpg",
  "episode_card_thumbnail": "https://image.tmdb.org/t/p/w185/xt90JqLL1r3bx7aiOXQttfbkHsU.jpg",
  "episode_list_thumbnail": "https://image.tmdb.org/t/p/w185/xt90JqLL1r3bx7aiOXQttfbkHsU.jpg",
  "video_player_thumbnail": null,
  "servers": [
    {
      "option": 1,
      "real_video": "https://short.icu/AOWEsEmK_"
    },
    {
      "option": 2,
      "real_video": "https://rubystm.com/e/wqptdiatt3ae.html"
    },
    {
      "option": 3,
      "real_video": "https://cloudy.upns.one/#lobk5z"
    },
    {
      "option": 4,
      "real_video": "https://strmup.to/AU0enTV6scEk1"
    },
    {
      "option": 5,
      "real_video": "https://turbovidhls.com/t/68b691fe9379e"
    },
    {
      "option": 6,
      "real_video": "https://vidmoly.net/embed-hrxk5spi52vw.html"
    },
    {
      "option": null,
      "real_video": "https://play.zephyrflick.top/video/aad64398a969ec3186800d412fa7ab31"
    }
  ]
}