{
  "series": "I've Been Killing Slimes for 300 Years and Maxed Out My Level",
  "thumbnail": "https://image.tmdb.org/t/p/w185/oN8fY2He8Fb87uL67I7ctf63mR4.jpg",
  "season": 2,
  "episode": 5,
  "episode_title": "Episode 5",
  "episode_main_poster": "https://image.tmdb.org/t/p/w185/oN8fY2He8Fb87uL67I7ctf63mR4.jpg",
  "episode_card_thumbnail": "https://image.tmdb.org/t/p/w185/dcoHuCUB9tD7hdyEFmJvJ762z1h.jpg",
  "episode_list_thumbnail": "https://image.tmdb.org/t/p/w185/dcoHuCUB9tD7hdyEFmJvJ762z1h.jpg",
  "video_player_thumbnail": null,
  "servers": [
    {
      "option": 1,
      "real_video": "https://short.icu/bK_iTchR5"
    },
    {
      "option": 2,
      "real_video": "https://rubystm.com/e/unebga29woy9.html"
    },
    {
      "option": 3,
      "real_video": "https://cloudy.upns.one/#bgtqes"
    },
    {
      "option": 4,
      "real_video": "https://gdmirrorbot.nl/embed/ymaa585"
    },
    {
      "option": 5,
      "real_video": "https://gdmirrorbot.nl/embed/v7xood0"
    },
    {
      "option": 6,
      "real_video": "https://gdmirrorbot.nl/embed/p6kk29i"
    },
    {
      "option": 7,
      "real_video": "https://emturbovid.com/t/6847ad8a9cf10"
    },
    {
      "option": 8,
      "real_video": "https://raretoonsindia.co/ex/vQ41lLtWQlRX7CC"
    },
    {
      "option": 9,
      "real_video": "https://play.zephyrflick.top/video/2677c94cc946bd788a3828099d6bcd49"
    },
    {
      "option": null,
      "real_video": "https://vidstreaming.xyz/v/1vKF7vSFEdEY/"
    }
  ]
}