{
  "series": "Naruto",
  "thumbnail": "https://image.tmdb.org/t/p/w185/vauCEnR7CiyBDzRCeElKkCaXIYu.jpg",
  "season": 3,
  "episode": 32,
  "episode_title": "Episode 32",
  "episode_main_poster": "https://image.tmdb.org/t/p/w185/vauCEnR7CiyBDzRCeElKkCaXIYu.jpg",
  "episode_card_thumbnail": "https://image.tmdb.org/t/p/w185/9BQKuRD5HNCwf6mThhroLIkj7Pa.jpg",
  "episode_list_thumbnail": "https://image.tmdb.org/t/p/w185/9BQKuRD5HNCwf6mThhroLIkj7Pa.jpg",
  "video_player_thumbnail": null,
  "servers": [
    {
      "option": 1,
      "real_video": "https://short.icu/Rd0nWENXi"
    },
    {
      "option": 2,
      "real_video": "https://gdmirrorbot.nl/embed/rw3tj4b"
    },
    {
      "option": 3,
      "real_video": "https://gdmirrorbot.nl/embed/cm3elt5"
    },
    {
      "option": 4,
      "real_video": "https://gdmirrorbot.nl/embed/rthqqw2"
    },
    {
      "option": 5,
      "real_video": "https://rubystm.com/e/twmsf2r7wegx.html"
    },
    {
      "option": 6,
      "real_video": "https://cloudy.upns.one/#dqu1cj"
    },
    {
      "option": 7,
      "real_video": "https://strmup.to/DcsHU4jdOFa3q"
    },
    {
      "option": 8,
      "real_video": "https://emturbovid.com/t/68e2a659a48b4"
    },
    {
      "option": 9,
      "real_video": "https://vidmoly.net/embed-wm5ahvqfy7sz.html"
    },
    {
      "option": null,
      "real_video": "https://play.zephyrflick.top/video/41f1f19176d383480afa65d325c06ed0"
    }
  ]
}