{
  "series": "Naruto",
  "thumbnail": "https://image.tmdb.org/t/p/w185/vauCEnR7CiyBDzRCeElKkCaXIYu.jpg",
  "season": 3,
  "episode": 26,
  "episode_title": "Episode 26",
  "episode_main_poster": "https://image.tmdb.org/t/p/w185/vauCEnR7CiyBDzRCeElKkCaXIYu.jpg",
  "episode_card_thumbnail": "https://image.tmdb.org/t/p/w185/4UemzF9CRd42xGxe15P5MG5S0V4.jpg",
  "episode_list_thumbnail": "https://image.tmdb.org/t/p/w185/4UemzF9CRd42xGxe15P5MG5S0V4.jpg",
  "video_player_thumbnail": null,
  "servers": [
    {
      "option": 1,
      "real_video": "https://short.icu/YzdB4hWEC"
    },
    {
      "option": 2,
      "real_video": "https://gdmirrorbot.nl/embed/p24cbx0"
    },
    {
      "option": 3,
      "real_video": "https://gdmirrorbot.nl/embed/l7iyrhq"
    },
    {
      "option": 4,
      "real_video": "https://gdmirrorbot.nl/embed/yen2ao8"
    },
    {
      "option": 5,
      "real_video": "https://rubystm.com/e/g9icxmfwgsp4.html"
    },
    {
      "option": 6,
      "real_video": "https://cloudy.upns.one/#xiyder"
    },
    {
      "option": 7,
      "real_video": "https://strmup.to/jQzmLES4rK2ID"
    },
    {
      "option": 8,
      "real_video": "https://emturbovid.com/t/68e2a650b4f4c"
    },
    {
      "option": 9,
      "real_video": "https://vidmoly.net/embed-3eodhoq0t04t.html"
    },
    {
      "option": null,
      "real_video": "https://play.zephyrflick.top/video/d34ab169b70c9dcd35e62896010cd9ff"
    }
  ]
}