{
  "series": "My Daemon",
  "thumbnail": "https://image.tmdb.org/t/p/w185/5bWTE3CwBM6z8lew9BPykujeNwG.jpg",
  "season": 1,
  "episode": 11,
  "episode_title": "Episode 11",
  "episode_main_poster": "https://image.tmdb.org/t/p/w185/5bWTE3CwBM6z8lew9BPykujeNwG.jpg",
  "episode_card_thumbnail": "https://image.tmdb.org/t/p/w185/ndQB8EgtbRbacNaC2aAQVD91Gyf.jpg",
  "episode_list_thumbnail": "https://image.tmdb.org/t/p/w185/ndQB8EgtbRbacNaC2aAQVD91Gyf.jpg",
  "video_player_thumbnail": null,
  "servers": [
    {
      "option": 1,
      "real_video": "https://rubystm.come/7xhb35ywic2i.html"
    },
    {
      "option": 2,
      "real_video": "https://short.icu/e9SGHDEIT"
    },
    {
      "option": 3,
      "real_video": "https://multimovies.cloud/e/s52n4soq2pbm"
    },
    {
      "option": 4,
      "real_video": "https://filemoon.to/e/2hx7z3flucdg/Toonhub4u_My_Daemon_S01E11_480p_NF_WEB-DL_Multi_Audio_ESub"
    },
    {
      "option": 5,
      "real_video": "https://filelions.online/v/y401abviynl7"
    },
    {
      "option": null,
      "real_video": "https://vidstreaming.xyz/v/O0oUTGGDVPxh/"
    }
  ]
}