{
  "series": "Digimon Adventure:",
  "thumbnail": "https://image.tmdb.org/t/p/w185/7Qspx2eFX0uBSQLLlAKnYrjZgse.jpg",
  "season": 1,
  "episode": 10,
  "episode_title": "Episode 10",
  "episode_main_poster": "https://image.tmdb.org/t/p/w185/7Qspx2eFX0uBSQLLlAKnYrjZgse.jpg",
  "episode_card_thumbnail": "https://image.tmdb.org/t/p/w185/svFE3H5yhdU2hkzAAMuDsUzd5OS.jpg",
  "episode_list_thumbnail": "https://image.tmdb.org/t/p/w185/svFE3H5yhdU2hkzAAMuDsUzd5OS.jpg",
  "video_player_thumbnail": null,
  "servers": [
    {
      "option": 1,
      "real_video": "https://vidstreaming.xyz/v/LkS8qdIU15en/"
    },
    {
      "option": 2,
      "real_video": "https://streamsb.net/e/uxn4v3h1cvpk.html"
    },
    {
      "option": 3,
      "real_video": "https://filemoon.to/e/9f6wkjx67jkf/_Toonhub4u__Digimon_Adventure__40_2020_41__Episode_10_Multi_Audio_480p.mp4"
    },
    {
      "option": null,
      "real_video": "https://play.zephyrflick.top/video/ad68473a64305626a27c32a5408552d7"
    }
  ]
}