{
  "title": "A Johnny Bravo Christmas",
  "description": "Watch A Johnny Bravo Christmas online for free in HD on ToonStream. Available in Hindi, Tamil, Telugu & More dubbed versions. Stream or Download now! On",
  "release_year": 2001,
  "genres": [
    "Amazon Prime Video",
    "Animation",
    "Animation & Cartoon Movies",
    "Comedy",
    "English",
    "Hindi"
  ],
  "thumbnail": "https://image.tmdb.org/t/p/w185/7OXm6NvEYOOnxiZh0fqhOGSxdEd.jpg",
  "movie_poster": "https://image.tmdb.org/t/p/w185/7OXm6NvEYOOnxiZh0fqhOGSxdEd.jpg",
  "tmdb_id": null,
  "tvdb_id": null,
  "languages": [],
  "url": "https://toonstream.love/movies/a-johnny-bravo-christmas/",
  "servers": [
    {
      "option": 1,
      "real_video": "https://vidstreaming.xyz/v/5aBEf1zYBq6l/"
    },
    {
      "option": 2,
      "real_video": "https://short.icu/mgzE2c_TL"
    },
    {
      "option": 3,
      "real_video": "https://rubystm.com/embed-8gkke0w32n8r.html"
    },
    {
      "option": 4,
      "real_video": "https://cloudy.upns.one/#mqnqd"
    },
    {
      "option": 5,
      "real_video": "https://gdmirrorbot.nl/embed/zuzkc29"
    },
    {
      "option": 6,
      "real_video": "https://emturbovid.com/t/676b767c85d0f"
    }
  ]
}