{
  "series": "Kaguya-sama: Love Is War Hindi Dub",
  "thumbnail": "https://image.tmdb.org/t/p/w185/5khbC6AuNgnvnoDbjIMKCOhEtIc.jpg",
  "season": 1,
  "episode": 1,
  "episode_title": "Episode 1",
  "episode_main_poster": "https://image.tmdb.org/t/p/w185/5khbC6AuNgnvnoDbjIMKCOhEtIc.jpg",
  "episode_card_thumbnail": "https://image.tmdb.org/t/p/w185/1tcnck8JUDtljCT8f621R00DXRz.jpg",
  "episode_list_thumbnail": "https://image.tmdb.org/t/p/w185/1tcnck8JUDtljCT8f621R00DXRz.jpg",
  "video_player_thumbnail": null,
  "servers": [
    {
      "option": 1,
      "real_video": "https://vidstreaming.xyz/v/2k3jMORjtxjp/"
    },
    {
      "option": 2,
      "real_video": "https://short.icu/FppqHTecx"
    },
    {
      "option": 3,
      "real_video": "https://rubystm.com/e/66cagnpi35dm.html"
    },
    {
      "option": 4,
      "real_video": "https://cloudy.upns.one/#pkwiev"
    },
    {
      "option": 5,
      "real_video": "https://gdmirrorbot.nl/embed/uwpeeex"
    },
    {
      "option": 6,
      "real_video": "https://gdmirrorbot.nl/embed/s65t6ht"
    },
    {
      "option": 7,
      "real_video": "https://gdmirrorbot.nl/embed/qi3nvj2"
    },
    {
      "option": 8,
      "real_video": "https://emturbovid.com/t/681b24694a0d8"
    },
    {
      "option": null,
      "real_video": "https://play.zephyrflick.top/video/c86038fe04bc7097e218b4fd6b767f4b"
    }
  ]
}