{
  "series": "Justice League",
  "thumbnail": "https://image.tmdb.org/t/p/w185/caIAQIoM9NLZofT8fz8t47W1gYe.jpg",
  "season": 1,
  "episode": 17,
  "episode_title": "Episode 17",
  "episode_main_poster": "https://image.tmdb.org/t/p/w185/caIAQIoM9NLZofT8fz8t47W1gYe.jpg",
  "episode_card_thumbnail": "https://image.tmdb.org/t/p/w185/c5wY3w6vp80bIVSZRKgvJCzpBJR.jpg",
  "episode_list_thumbnail": "https://image.tmdb.org/t/p/w185/c5wY3w6vp80bIVSZRKgvJCzpBJR.jpg",
  "video_player_thumbnail": null,
  "servers": [
    {
      "option": 1,
      "real_video": "https://short.icu/5CbH805x0"
    },
    {
      "option": 2,
      "real_video": "https://gdmirrorbot.nl/embed/tlnfznh"
    },
    {
      "option": 3,
      "real_video": "https://gdmirrorbot.nl/embed/wesqo64"
    },
    {
      "option": 4,
      "real_video": "https://gdmirrorbot.nl/embed/x9xwpce"
    },
    {
      "option": null,
      "real_video": "https://vidstreaming.xyz/v/AoXV9RFG1lWt/"
    }
  ]
}