{
  "series": "Naruto Shippūden",
  "thumbnail": "https://image.tmdb.org/t/p/w185/rXD6lcg6zhRE8NDRVlQPNkViC3s.jpg",
  "season": 5,
  "episode": 6,
  "episode_title": "Episode 6",
  "episode_main_poster": "https://image.tmdb.org/t/p/w185/rXD6lcg6zhRE8NDRVlQPNkViC3s.jpg",
  "episode_card_thumbnail": "https://image.tmdb.org/t/p/w185/e7WOKR7OMiz4jMGAlsrOlgAljki.jpg",
  "episode_list_thumbnail": "https://image.tmdb.org/t/p/w185/e7WOKR7OMiz4jMGAlsrOlgAljki.jpg",
  "video_player_thumbnail": null,
  "servers": [
    {
      "option": 1,
      "real_video": "https://short.icu/jEWKQms6yX"
    },
    {
      "option": 2,
      "real_video": "https://gdmirrorbot.nl/embed/e5utvwx"
    },
    {
      "option": 3,
      "real_video": "https://gdmirrorbot.nl/embed/v2d542j"
    },
    {
      "option": 4,
      "real_video": "https://gdmirrorbot.nl/embed/y7es0ms"
    },
    {
      "option": 5,
      "real_video": "https://rubystm.com/e/gh4w7rbplvfm.html"
    },
    {
      "option": 6,
      "real_video": "https://cloudy.upns.one/#9dppfp"
    },
    {
      "option": 7,
      "real_video": "https://strmup.to/UHOxGmu1FYiwo"
    },
    {
      "option": 8,
      "real_video": "https://turbovidhls.com/t/68e5181e89779"
    },
    {
      "option": 9,
      "real_video": "https://vidmoly.net/embed-xg9er3epr20l.html"
    },
    {
      "option": null,
      "real_video": "https://play.zephyrflick.top/video/7f24d240521d99071c93af3917215ef7"
    }
  ]
}