{
  "series": "Boruto: Naruto Next Generations",
  "thumbnail": "https://image.tmdb.org/t/p/w185/e0B6i48kxdRkMcK4tR4YNfXGWOc.jpg",
  "season": 1,
  "episode": 95,
  "episode_title": "Episode 95",
  "episode_main_poster": "https://image.tmdb.org/t/p/w185/e0B6i48kxdRkMcK4tR4YNfXGWOc.jpg",
  "episode_card_thumbnail": "https://image.tmdb.org/t/p/w185/4Iz7bLLqfNfEA2A1g1U5UDA45P0.jpg",
  "episode_list_thumbnail": "https://image.tmdb.org/t/p/w185/4Iz7bLLqfNfEA2A1g1U5UDA45P0.jpg",
  "video_player_thumbnail": null,
  "servers": [
    {
      "option": 1,
      "real_video": "https://short.icu/4V9a8R2Fr"
    },
    {
      "option": null,
      "real_video": "https://vidstreaming.xyz/v/e2QGY2jAKHkU/"
    }
  ]
}