{
  "series": "Naruto Shippūden",
  "thumbnail": "https://image.tmdb.org/t/p/w185/rXD6lcg6zhRE8NDRVlQPNkViC3s.jpg",
  "season": 2,
  "episode": 1,
  "episode_title": "Episode 1",
  "episode_main_poster": "https://image.tmdb.org/t/p/w185/rXD6lcg6zhRE8NDRVlQPNkViC3s.jpg",
  "episode_card_thumbnail": "https://image.tmdb.org/t/p/w185/97O9irZPuV08ZLPQIPea434UG6R.jpg",
  "episode_list_thumbnail": "https://image.tmdb.org/t/p/w185/97O9irZPuV08ZLPQIPea434UG6R.jpg",
  "video_player_thumbnail": null,
  "servers": [
    {
      "option": 1,
      "real_video": "https://short.icu/rb21VTfhc"
    },
    {
      "option": 2,
      "real_video": "https://gdmirrorbot.nl/embed/k28d2hq"
    },
    {
      "option": 3,
      "real_video": "https://gdmirrorbot.nl/embed/q8vxtek"
    },
    {
      "option": 4,
      "real_video": "https://gdmirrorbot.nl/embed/x6jdm7q"
    },
    {
      "option": 5,
      "real_video": "https://short.icu/Ph7Yb-Kw7"
    },
    {
      "option": 6,
      "real_video": "https://rubystm.com/ehonmiuv389w8.html"
    },
    {
      "option": 7,
      "real_video": "https://cloudy.upns.one/#smr5c"
    },
    {
      "option": 8,
      "real_video": "https://gdmirrorbot.nl/embed/wy73yub"
    },
    {
      "option": 9,
      "real_video": "https://emturbovid.com/t/67971a9ccaa05"
    },
    {
      "option": 10,
      "real_video": "https://rubystm.com/e/71e1awfq4t3i.html"
    },
    {
      "option": 11,
      "real_video": "https://cloudy.upns.one/#lossal"
    },
    {
      "option": 12,
      "real_video": "https://strmup.to/UnXbV8QN2yB1L"
    },
    {
      "option": 13,
      "real_video": "https://turbovidhls.com/t/68e514b09092d"
    },
    {
      "option": 14,
      "real_video": "https://vidmoly.net/embed-kg5kei1i2hu1.html"
    },
    {
      "option": null,
      "real_video": "https://play.zephyrflick.top/video/05f971b5ec196b8c65b75d2ef8267331"
    }
  ]
}