{
  "series": "Ghost in the Shell: Stand Alone Complex",
  "thumbnail": "https://image.tmdb.org/t/p/w185/mzZbdPUtAD5CGyIjGR98FpzKahi.jpg",
  "season": 1,
  "episode": 21,
  "episode_title": "Episode 21",
  "episode_main_poster": "https://image.tmdb.org/t/p/w185/mzZbdPUtAD5CGyIjGR98FpzKahi.jpg",
  "episode_card_thumbnail": "https://image.tmdb.org/t/p/w185/ukHLowOGcVtEFAc927rfKLE6DUo.jpg",
  "episode_list_thumbnail": "https://image.tmdb.org/t/p/w185/ukHLowOGcVtEFAc927rfKLE6DUo.jpg",
  "video_player_thumbnail": null,
  "servers": [
    {
      "option": 1,
      "real_video": "https://vidstreaming.xyz/v/wabf9V3gh8wp/"
    },
    {
      "option": 2,
      "real_video": "https://short.icu/kNPRIsJ3k"
    },
    {
      "option": 3,
      "real_video": "https://rubystm.com/e/8pvoit7nw6z4.html"
    },
    {
      "option": 4,
      "real_video": "https://cloudy.upns.one/#c5pns8"
    },
    {
      "option": 5,
      "real_video": "https://gdmirrorbot.nl/embed/w239t9z"
    },
    {
      "option": 6,
      "real_video": "https://gdmirrorbot.nl/embed/yytczz2"
    },
    {
      "option": 7,
      "real_video": "https://gdmirrorbot.nl/embed/vmkwbeg"
    },
    {
      "option": 8,
      "real_video": "https://emturbovid.com/t/68319b90bca66"
    },
    {
      "option": null,
      "real_video": "https://play.zephyrflick.top/video/8cb3522da182ff9ea5925bbd8975b203"
    }
  ]
}