{
  "series": "Record of Grancrest War",
  "thumbnail": "https://image.tmdb.org/t/p/w185/tECUAfNnSrNp7IS1HwXboLvg1FQ.jpg",
  "season": 1,
  "episode": 6,
  "episode_title": "Episode 6",
  "episode_main_poster": "https://image.tmdb.org/t/p/w185/tECUAfNnSrNp7IS1HwXboLvg1FQ.jpg",
  "episode_card_thumbnail": "https://image.tmdb.org/t/p/w185/on2FaVEGs1raGaCxcK3I9DUMzvz.jpg",
  "episode_list_thumbnail": "https://image.tmdb.org/t/p/w185/on2FaVEGs1raGaCxcK3I9DUMzvz.jpg",
  "video_player_thumbnail": null,
  "servers": [
    {
      "option": 1,
      "real_video": "https://short.icu/tJG3gE6Hy"
    },
    {
      "option": 2,
      "real_video": "https://gdmirrorbot.nl/embed/i6rifnd"
    },
    {
      "option": null,
      "real_video": "https://vidstreaming.xyz/v/02a5lZrugF5P/"
    }
  ]
}