{
  "series": "Hunter x Hunter Hindi Dub",
  "thumbnail": "https://image.tmdb.org/t/p/w185/9dubj2UQ2xJkzT1AEng6DaGRvLa.jpg",
  "season": 2,
  "episode": 24,
  "episode_title": "Episode 24",
  "episode_main_poster": "https://image.tmdb.org/t/p/w185/9dubj2UQ2xJkzT1AEng6DaGRvLa.jpg",
  "episode_card_thumbnail": "https://image.tmdb.org/t/p/w185/6OKfLWaxyDeCtN33oIsbZt8D9uX.jpg",
  "episode_list_thumbnail": "https://image.tmdb.org/t/p/w185/6OKfLWaxyDeCtN33oIsbZt8D9uX.jpg",
  "video_player_thumbnail": null,
  "servers": [
    {
      "option": 1,
      "real_video": "https://short.icu/cOe66MsQZ"
    },
    {
      "option": 2,
      "real_video": "https://rubystm.com/e/dlemjs5rhrnu.html"
    },
    {
      "option": 3,
      "real_video": "https://cloudy.upns.one/#qtns9l"
    },
    {
      "option": 4,
      "real_video": "https://strmup.to/HVjP0Jt4e8EI5"
    },
    {
      "option": 5,
      "real_video": "https://gdmirrorbot.nl/embed/ppde3cg"
    },
    {
      "option": 6,
      "real_video": "https://gdmirrorbot.nl/embed/u5ydbjk"
    },
    {
      "option": 7,
      "real_video": "https://gdmirrorbot.nl/embed/wyk68n6"
    },
    {
      "option": 8,
      "real_video": "https://emturbovid.com/t/68e3e230b1e6c"
    },
    {
      "option": 9,
      "real_video": "https://vidmoly.net/embed-6is0t0keh9t3.html"
    },
    {
      "option": null,
      "real_video": "https://play.zephyrflick.top/video/062a781089e948d29ba79b89499a1120"
    }
  ]
}