{
  "series": "The Dangers in My Heart",
  "thumbnail": "https://image.tmdb.org/t/p/w185/mKhMmREBOKXtp3tlv9rnLRxZec5.jpg",
  "season": 1,
  "episode": 15,
  "episode_title": "Episode 15",
  "episode_main_poster": "https://image.tmdb.org/t/p/w185/mKhMmREBOKXtp3tlv9rnLRxZec5.jpg",
  "episode_card_thumbnail": "https://image.tmdb.org/t/p/w185/6rkLa1vEsa08tlzpTwPuohzbrBq.jpg",
  "episode_list_thumbnail": "https://image.tmdb.org/t/p/w185/6rkLa1vEsa08tlzpTwPuohzbrBq.jpg",
  "video_player_thumbnail": null,
  "servers": [
    {
      "option": 1,
      "real_video": "https://short.icu/tkS2IdcYL"
    },
    {
      "option": 2,
      "real_video": "https://gdmirrorbot.nl/embed/pmuwx0v"
    },
    {
      "option": 3,
      "real_video": "https://vidstreaming.xyz/v/qWxrPGVJ9u4r/"
    },
    {
      "option": 4,
      "real_video": "https://short.icu/nU480Qru4"
    },
    {
      "option": 5,
      "real_video": "https://gdmirrorbot.nl/embed/jaj65zl"
    },
    {
      "option": null,
      "real_video": "https://vidstreaming.xyz/v/doxVpp6awq7b/"
    }
  ]
}