{
  "series": "One Piece",
  "thumbnail": "https://image.tmdb.org/t/p/w185/dum1wnm6kJOUos0XJqjB8s2UWi9.jpg",
  "season": 11,
  "episode": 2,
  "episode_title": "Episode 2",
  "episode_main_poster": "https://image.tmdb.org/t/p/w185/dum1wnm6kJOUos0XJqjB8s2UWi9.jpg",
  "episode_card_thumbnail": "https://image.tmdb.org/t/p/w185/eCsGyyrzIUpmLr2AltCmA7UX89K.jpg",
  "episode_list_thumbnail": "https://image.tmdb.org/t/p/w185/eCsGyyrzIUpmLr2AltCmA7UX89K.jpg",
  "video_player_thumbnail": null,
  "servers": [
    {
      "option": 1,
      "real_video": "https://rubystm.com/e/hpqikdeo06d5.html"
    },
    {
      "option": 2,
      "real_video": "https://strmup.to/2oGmSU2z5Zof"
    },
    {
      "option": null,
      "real_video": "https://vidstreaming.xyz/v/fpeNhLa0NfnM/"
    }
  ]
}