{
  "series": "My Teen Romantic Comedy SNAFU English Dub",
  "thumbnail": "https://image.tmdb.org/t/p/w185/8knvr1LbnPD8SZjZlkD3cOt3TYu.jpg",
  "season": 2,
  "episode": 13,
  "episode_title": "Episode 13",
  "episode_main_poster": "https://image.tmdb.org/t/p/w185/8knvr1LbnPD8SZjZlkD3cOt3TYu.jpg",
  "episode_card_thumbnail": "https://image.tmdb.org/t/p/w185/t5eZjZy1kAVJE4e8x08vUVaNU6i.jpg",
  "episode_list_thumbnail": "https://image.tmdb.org/t/p/w185/t5eZjZy1kAVJE4e8x08vUVaNU6i.jpg",
  "video_player_thumbnail": null,
  "servers": [
    {
      "option": null,
      "real_video": "https://www.youtube.com/embed/1N3OsqTfHXA"
    }
  ]
}