{
  "series": "One Piece",
  "thumbnail": "https://image.tmdb.org/t/p/w185/dum1wnm6kJOUos0XJqjB8s2UWi9.jpg",
  "season": 14,
  "episode": 21,
  "episode_title": "Episode 21",
  "episode_main_poster": "https://image.tmdb.org/t/p/w185/dum1wnm6kJOUos0XJqjB8s2UWi9.jpg",
  "episode_card_thumbnail": "https://image.tmdb.org/t/p/w185/d5fWH2oT3d9OLDnc5zeCyWJzoa1.jpg",
  "episode_list_thumbnail": "https://image.tmdb.org/t/p/w185/d5fWH2oT3d9OLDnc5zeCyWJzoa1.jpg",
  "video_player_thumbnail": null,
  "servers": [
    {
      "option": 1,
      "real_video": "https://rubystm.com/e/qzp86j6rux2v.html"
    },
    {
      "option": 2,
      "real_video": "https://strmup.to/xXl9y7brjhWT"
    },
    {
      "option": null,
      "real_video": "https://vidstreaming.xyz/v/vrKBWBazNEAV/"
    }
  ]
}