{
  "series": "YAIBA: Samurai Legend",
  "thumbnail": "https://image.tmdb.org/t/p/w185/cxD3FQP4hDU5hSABwdQCvGrrnz6.jpg",
  "season": 1,
  "episode": 11,
  "episode_title": "Episode 11",
  "episode_main_poster": "https://image.tmdb.org/t/p/w185/cxD3FQP4hDU5hSABwdQCvGrrnz6.jpg",
  "episode_card_thumbnail": "https://image.tmdb.org/t/p/w185/hbFs7EfxNk9IoGs3n6WJqbnXdx6.jpg",
  "episode_list_thumbnail": "https://image.tmdb.org/t/p/w185/hbFs7EfxNk9IoGs3n6WJqbnXdx6.jpg",
  "video_player_thumbnail": null,
  "servers": [
    {
      "option": 1,
      "real_video": "https://short.icu/StDtr4Nti"
    },
    {
      "option": 2,
      "real_video": "https://rubystm.com/e/mxsqh93hvfko.html"
    },
    {
      "option": 3,
      "real_video": "https://cloudy.upns.one/#h9t1h6"
    },
    {
      "option": 4,
      "real_video": "https://strmup.to/k4o8aFJzlx9vT"
    },
    {
      "option": 5,
      "real_video": "https://gdmirrorbot.nl/embed/svd9xhy"
    },
    {
      "option": 6,
      "real_video": "https://gdmirrorbot.nl/embed/b5mjjqv"
    },
    {
      "option": 7,
      "real_video": "https://gdmirrorbot.nl/embed/rln770a"
    },
    {
      "option": 8,
      "real_video": "https://emturbovid.com/t/6896151f4e343"
    },
    {
      "option": 9,
      "real_video": "https://vidmoly.net/embed-e8rmjj4zr34w.html"
    },
    {
      "option": null,
      "real_video": "https://play.zephyrflick.top/video/7d5a3c270200daf0475c1f217910f982"
    }
  ]
}